crsq_arithmetic/__init__.py
crsq_arithmetic/absolute.py
crsq_arithmetic/adder.py
crsq_arithmetic/ast.py
crsq_arithmetic/bit_ops.py
crsq_arithmetic/cdk_absolute.py
crsq_arithmetic/cdk_adder.py
crsq_arithmetic/cdk_comparator.py
crsq_arithmetic/cdk_divider.py
crsq_arithmetic/cdk_subtractor.py
crsq_arithmetic/divider.py
crsq_arithmetic/multiplier.py
crsq_arithmetic/square.py
crsq_arithmetic/square2.py
crsq_arithmetic/square_root.py
crsq_arithmetic/subtractor.py
crsq_arithmetic/test_tools.py
crsq_arithmetic/utils.py
crsq_arithmetic/vsqrom.py
crsq_arithmetic-0.2.0.dist-info/METADATA
crsq_arithmetic-0.2.0.dist-info/WHEEL
crsq_arithmetic-0.2.0.dist-info/licenses/LICENSE
crsq_arithmetic-0.2.0.dist-info/RECORD
